[
  {
    "id": "1000",
    "question": "Would you recommend me as a candidate to your friend? (0-10)",
    "start": "1460169437190",
    "end": "1460176637190",
    "polls_sent": 10,
    "polls_responded": 4
  },
  {
    "id": "1001",
    "question": "How much do you care about the 2nd Amendment? (0-10)",
    "start": "1459737437190",
    "end": "1459744637190",
    "polls_sent": 10,
    "polls_responded": 2
  },
  {
    "id": "1002",
    "question": "Would you recommend me as a candidate to your friend? (0-10)",
    "start": "1459564637190",
    "end": "1459571837190",
    "polls_sent": 10,
    "polls_responded": 7
  },
  {
    "id": "1003",
    "question": "Would you recommend me as a candidate to your friend? (0-10)",
    "start": "1459478237190",
    "end": "1459485437190",
    "polls_sent": 10,
    "polls_responded": 2
  },
  {
    "id": "1004",
    "question": "Would you recommend me as a candidate to your friend? (0-10)",
    "start": "1459478237190",
    "end": "1459485437190",
    "polls_sent": 10,
    "polls_responded": 7
  },
  {
    "id": "1005",
    "question": "Do you approve of my campaign so far? (0-10)",
    "start": "1459391837190",
    "end": "1459399037190",
    "polls_sent": 10,
    "polls_responded": 6
  },
  {
    "id": "1006",
    "question": "How did I do in last night's debate? (0-10)",
    "start": "1459219037190",
    "end": "1459226237190",
    "polls_sent": 10,
    "polls_responded": 7
  },
  {
    "id": "1007",
    "question": "How did I do in last night's debate? (0-10)",
    "start": "1458614237190",
    "end": "1458621437190",
    "polls_sent": 10,
    "polls_responded": 3
  },
  {
    "id": "1008",
    "question": "How did I do in last night's debate? (0-10)",
    "start": "1458614237190",
    "end": "1458621437190",
    "polls_sent": 10,
    "polls_responded": 1
  },
  {
    "id": "1009",
    "question": "Do you approve of my campaign so far? (0-10)",
    "start": "1458182237190",
    "end": "1458189437190",
    "polls_sent": 10,
    "polls_responded": 8
  }
]