[
  {
    "id": "100010",
    "user": {
      "id": "1021",
      "first_name": "CHRISTINE",
      "last_name": "THOMPSON",
      "party": "REPUBLICAN",
      "gender": "female",
      "zip": "94137"
    },
    "userId": "1021",
    "poll": {
      "id": "1000",
      "question": "Would you recommend me as a candidate to your friend? (0-10)",
      "start": "1460169437190",
      "end": "1460176637190",
      "polls_sent": 10,
      "polls_responded": 4
    },
    "pollId": "1000",
    "message": "1 (^*%&$^#^%$#^)",
    "value": "1"
  },
  {
    "id": "100020",
    "user": {
      "id": "1097",
      "first_name": "MELANIE",
      "last_name": "JOHNSON",
      "party": "LIBERTARIAN",
      "gender": "female",
      "zip": "94197"
    },
    "userId": "1097",
    "poll": {
      "id": "1000",
      "question": "Would you recommend me as a candidate to your friend? (0-10)",
      "start": "1460169437190",
      "end": "1460176637190",
      "polls_sent": 10,
      "polls_responded": 4
    },
    "pollId": "1000",
    "message": "9 STOP sending me these",
    "value": "9"
  },
  {
    "id": "100030",
    "user": {
      "id": "1033",
      "first_name": "CHRISTINE",
      "last_name": "WILLIAMS",
      "party": "DEMOCRAT",
      "gender": "female",
      "zip": "94168"
    },
    "userId": "1033",
    "poll": {
      "id": "1000",
      "question": "Would you recommend me as a candidate to your friend? (0-10)",
      "start": "1460169437190",
      "end": "1460176637190",
      "polls_sent": 10,
      "polls_responded": 4
    },
    "pollId": "1000",
    "message": "9 I could do better",
    "value": "9"
  },
  {
    "id": "100040",
    "user": {
      "id": "1036",
      "first_name": "GLENN",
      "last_name": "DAVIS",
      "party": "INDEPENDENT",
      "gender": "female",
      "zip": "94122"
    },
    "userId": "1036",
    "poll": {
      "id": "1000",
      "question": "Would you recommend me as a candidate to your friend? (0-10)",
      "start": "1460169437190",
      "end": "1460176637190",
      "polls_sent": 10,
      "polls_responded": 4
    },
    "pollId": "1000",
    "message": "0 #boo",
    "value": "0"
  },
  {
    "id": "100110",
    "user": {
      "id": "1048",
      "first_name": "CLAIRE",
      "last_name": "HILL",
      "party": "GREEN",
      "gender": "female",
      "zip": "94170"
    },
    "userId": "1048",
    "poll": {
      "id": "1001",
      "question": "How much do you care about the 2nd Amendment? (0-10)",
      "start": "1459737437190",
      "end": "1459744637190",
      "polls_sent": 10,
      "polls_responded": 2
    },
    "pollId": "1001",
    "message": "5 #boo",
    "value": "5"
  },
  {
    "id": "100120",
    "user": {
      "id": "1080",
      "first_name": "LEONARD",
      "last_name": "BAKER",
      "party": "LIBERTARIAN",
      "gender": "female",
      "zip": "94160"
    },
    "userId": "1080",
    "poll": {
      "id": "1001",
      "question": "How much do you care about the 2nd Amendment? (0-10)",
      "start": "1459737437190",
      "end": "1459744637190",
      "polls_sent": 10,
      "polls_responded": 2
    },
    "pollId": "1001",
    "message": "2 (^*%&$^#^%$#^)",
    "value": "2"
  },
  {
    "id": "100210",
    "user": {
      "id": "1076",
      "first_name": "MINNIE",
      "last_name": "HILL",
      "party": "REPUBLICAN",
      "gender": "female",
      "zip": "94129"
    },
    "userId": "1076",
    "poll": {
      "id": "1002",
      "question": "Would you recommend me as a candidate to your friend? (0-10)",
      "start": "1459564637190",
      "end": "1459571837190",
      "polls_sent": 10,
      "polls_responded": 7
    },
    "pollId": "1002",
    "message": "7 I love you",
    "value": "7"
  },
  {
    "id": "100220",
    "user": {
      "id": "1031",
      "first_name": "DEVIN",
      "last_name": "WHITE",
      "party": "DEMOCRAT",
      "gender": "female",
      "zip": "94146"
    },
    "userId": "1031",
    "poll": {
      "id": "1002",
      "question": "Would you recommend me as a candidate to your friend? (0-10)",
      "start": "1459564637190",
      "end": "1459571837190",
      "polls_sent": 10,
      "polls_responded": 7
    },
    "pollId": "1002",
    "message": "2 #winning",
    "value": "2"
  },
  {
    "id": "100230",
    "user": {
      "id": "1033",
      "first_name": "CHRISTINE",
      "last_name": "WILLIAMS",
      "party": "DEMOCRAT",
      "gender": "female",
      "zip": "94168"
    },
    "userId": "1033",
    "poll": {
      "id": "1002",
      "question": "Would you recommend me as a candidate to your friend? (0-10)",
      "start": "1459564637190",
      "end": "1459571837190",
      "polls_sent": 10,
      "polls_responded": 7
    },
    "pollId": "1002",
    "message": "0 STOP sending me these",
    "value": "0"
  },
  {
    "id": "100240",
    "user": {
      "id": "1078",
      "first_name": "JOE",
      "last_name": "THOMPSON",
      "party": "DEMOCRAT",
      "gender": "female",
      "zip": "94180"
    },
    "userId": "1078",
    "poll": {
      "id": "1002",
      "question": "Would you recommend me as a candidate to your friend? (0-10)",
      "start": "1459564637190",
      "end": "1459571837190",
      "polls_sent": 10,
      "polls_responded": 7
    },
    "pollId": "1002",
    "message": "3 (^*%&$^#^%$#^)",
    "value": "3"
  },
  {
    "id": "100250",
    "user": {
      "id": "1050",
      "first_name": "FRANK",
      "last_name": "HILL",
      "party": "DEMOCRAT",
      "gender": "female",
      "zip": "94133"
    },
    "userId": "1050",
    "poll": {
      "id": "1002",
      "question": "Would you recommend me as a candidate to your friend? (0-10)",
      "start": "1459564637190",
      "end": "1459571837190",
      "polls_sent": 10,
      "polls_responded": 7
    },
    "pollId": "1002",
    "message": "9 #winning",
    "value": "9"
  },
  {
    "id": "100260",
    "user": {
      "id": "1047",
      "first_name": "DANNY",
      "last_name": "TAYLOR",
      "party": "LIBERTARIAN",
      "gender": "female",
      "zip": "94191"
    },
    "userId": "1047",
    "poll": {
      "id": "1002",
      "question": "Would you recommend me as a candidate to your friend? (0-10)",
      "start": "1459564637190",
      "end": "1459571837190",
      "polls_sent": 10,
      "polls_responded": 7
    },
    "pollId": "1002",
    "message": "0 I love you",
    "value": "0"
  },
  {
    "id": "100270",
    "user": {
      "id": "1084",
      "first_name": "JOE",
      "last_name": "JOHNSON",
      "party": "DEMOCRAT",
      "gender": "female",
      "zip": "94139"
    },
    "userId": "1084",
    "poll": {
      "id": "1002",
      "question": "Would you recommend me as a candidate to your friend? (0-10)",
      "start": "1459564637190",
      "end": "1459571837190",
      "polls_sent": 10,
      "polls_responded": 7
    },
    "pollId": "1002",
    "message": "5 STOP sending me these",
    "value": "5"
  },
  {
    "id": "100310",
    "user": {
      "id": "1041",
      "first_name": "GLENN",
      "last_name": "LUBY",
      "party": "INDEPENDENT",
      "gender": "female",
      "zip": "94138"
    },
    "userId": "1041",
    "poll": {
      "id": "1003",
      "question": "Would you recommend me as a candidate to your friend? (0-10)",
      "start": "1459478237190",
      "end": "1459485437190",
      "polls_sent": 10,
      "polls_responded": 2
    },
    "pollId": "1003",
    "message": "9 I want to hear more about abortion",
    "value": "9"
  },
  {
    "id": "100320",
    "user": {
      "id": "1014",
      "first_name": "PHIL",
      "last_name": "JONES",
      "party": "INDEPENDENT",
      "gender": "female",
      "zip": "9419"
    },
    "userId": "1014",
    "poll": {
      "id": "1003",
      "question": "Would you recommend me as a candidate to your friend? (0-10)",
      "start": "1459478237190",
      "end": "1459485437190",
      "polls_sent": 10,
      "polls_responded": 2
    },
    "pollId": "1003",
    "message": "0 (^*%&$^#^%$#^)",
    "value": "0"
  },
  {
    "id": "100410",
    "user": {
      "id": "1085",
      "first_name": "SALLY",
      "last_name": "WILLIAMS",
      "party": "GREEN",
      "gender": "female",
      "zip": "94144"
    },
    "userId": "1085",
    "poll": {
      "id": "1004",
      "question": "Would you recommend me as a candidate to your friend? (0-10)",
      "start": "1459478237190",
      "end": "1459485437190",
      "polls_sent": 10,
      "polls_responded": 7
    },
    "pollId": "1004",
    "message": "1 STOP sending me these",
    "value": "1"
  },
  {
    "id": "100420",
    "user": {
      "id": "1063",
      "first_name": "RACHEL",
      "last_name": "ALLEN",
      "party": "GREEN",
      "gender": "female",
      "zip": "94164"
    },
    "userId": "1063",
    "poll": {
      "id": "1004",
      "question": "Would you recommend me as a candidate to your friend? (0-10)",
      "start": "1459478237190",
      "end": "1459485437190",
      "polls_sent": 10,
      "polls_responded": 7
    },
    "pollId": "1004",
    "message": "1 #winning",
    "value": "1"
  },
  {
    "id": "100430",
    "user": {
      "id": "1081",
      "first_name": "MELANIE",
      "last_name": "KING",
      "party": "DEMOCRAT",
      "gender": "female",
      "zip": "94169"
    },
    "userId": "1081",
    "poll": {
      "id": "1004",
      "question": "Would you recommend me as a candidate to your friend? (0-10)",
      "start": "1459478237190",
      "end": "1459485437190",
      "polls_sent": 10,
      "polls_responded": 7
    },
    "pollId": "1004",
    "message": "10 I want to hear more about abortion",
    "value": "10"
  },
  {
    "id": "100440",
    "user": {
      "id": "1097",
      "first_name": "MELANIE",
      "last_name": "JOHNSON",
      "party": "LIBERTARIAN",
      "gender": "female",
      "zip": "94197"
    },
    "userId": "1097",
    "poll": {
      "id": "1004",
      "question": "Would you recommend me as a candidate to your friend? (0-10)",
      "start": "1459478237190",
      "end": "1459485437190",
      "polls_sent": 10,
      "polls_responded": 7
    },
    "pollId": "1004",
    "message": "4 STOP sending me these",
    "value": "4"
  },
  {
    "id": "100450",
    "user": {
      "id": "1068",
      "first_name": "MELANIE",
      "last_name": "WRIGHT",
      "party": "INDEPENDENT",
      "gender": "female",
      "zip": "94167"
    },
    "userId": "1068",
    "poll": {
      "id": "1004",
      "question": "Would you recommend me as a candidate to your friend? (0-10)",
      "start": "1459478237190",
      "end": "1459485437190",
      "polls_sent": 10,
      "polls_responded": 7
    },
    "pollId": "1004",
    "message": "8 STOP sending me these",
    "value": "8"
  },
  {
    "id": "100460",
    "user": {
      "id": "1090",
      "first_name": "DANNY",
      "last_name": "FUJITA",
      "party": "REPUBLICAN",
      "gender": "female",
      "zip": "94198"
    },
    "userId": "1090",
    "poll": {
      "id": "1004",
      "question": "Would you recommend me as a candidate to your friend? (0-10)",
      "start": "1459478237190",
      "end": "1459485437190",
      "polls_sent": 10,
      "polls_responded": 7
    },
    "pollId": "1004",
    "message": "8",
    "value": "8"
  },
  {
    "id": "100470",
    "user": {
      "id": "1082",
      "first_name": "RACHEL",
      "last_name": "THOMPSON",
      "party": "GREEN",
      "gender": "female",
      "zip": "94184"
    },
    "userId": "1082",
    "poll": {
      "id": "1004",
      "question": "Would you recommend me as a candidate to your friend? (0-10)",
      "start": "1459478237190",
      "end": "1459485437190",
      "polls_sent": 10,
      "polls_responded": 7
    },
    "pollId": "1004",
    "message": "8 STOP sending me these",
    "value": "8"
  },
  {
    "id": "100510",
    "user": {
      "id": "1006",
      "first_name": "CAROLINE",
      "last_name": "DAVIS",
      "party": "DEMOCRAT",
      "gender": "female",
      "zip": "94174"
    },
    "userId": "1006",
    "poll": {
      "id": "1005",
      "question": "Do you approve of my campaign so far? (0-10)",
      "start": "1459391837190",
      "end": "1459399037190",
      "polls_sent": 10,
      "polls_responded": 6
    },
    "pollId": "1005",
    "message": "4 I could do better",
    "value": "4"
  },
  {
    "id": "100520",
    "user": {
      "id": "1093",
      "first_name": "MELANIE",
      "last_name": "HALL",
      "party": "INDEPENDENT",
      "gender": "female",
      "zip": "94173"
    },
    "userId": "1093",
    "poll": {
      "id": "1005",
      "question": "Do you approve of my campaign so far? (0-10)",
      "start": "1459391837190",
      "end": "1459399037190",
      "polls_sent": 10,
      "polls_responded": 6
    },
    "pollId": "1005",
    "message": "4 (^*%&$^#^%$#^)",
    "value": "4"
  },
  {
    "id": "100530",
    "user": {
      "id": "1004",
      "first_name": "LEONARD",
      "last_name": "FUJITA",
      "party": "REPUBLICAN",
      "gender": "female",
      "zip": "94199"
    },
    "userId": "1004",
    "poll": {
      "id": "1005",
      "question": "Do you approve of my campaign so far? (0-10)",
      "start": "1459391837190",
      "end": "1459399037190",
      "polls_sent": 10,
      "polls_responded": 6
    },
    "pollId": "1005",
    "message": "10 STOP sending me these",
    "value": "10"
  },
  {
    "id": "100540",
    "user": {
      "id": "1070",
      "first_name": "SUSAN",
      "last_name": "WILSON",
      "party": "REPUBLICAN",
      "gender": "female",
      "zip": "94199"
    },
    "userId": "1070",
    "poll": {
      "id": "1005",
      "question": "Do you approve of my campaign so far? (0-10)",
      "start": "1459391837190",
      "end": "1459399037190",
      "polls_sent": 10,
      "polls_responded": 6
    },
    "pollId": "1005",
    "message": "10 #winning",
    "value": "10"
  },
  {
    "id": "100550",
    "user": {
      "id": "1042",
      "first_name": "DANNY",
      "last_name": "VIK",
      "party": "DEMOCRAT",
      "gender": "female",
      "zip": "94145"
    },
    "userId": "1042",
    "poll": {
      "id": "1005",
      "question": "Do you approve of my campaign so far? (0-10)",
      "start": "1459391837190",
      "end": "1459399037190",
      "polls_sent": 10,
      "polls_responded": 6
    },
    "pollId": "1005",
    "message": "0 (^*%&$^#^%$#^)",
    "value": "0"
  },
  {
    "id": "100560",
    "user": {
      "id": "1055",
      "first_name": "MINNIE",
      "last_name": "LEE",
      "party": "REPUBLICAN",
      "gender": "female",
      "zip": "94159"
    },
    "userId": "1055",
    "poll": {
      "id": "1005",
      "question": "Do you approve of my campaign so far? (0-10)",
      "start": "1459391837190",
      "end": "1459399037190",
      "polls_sent": 10,
      "polls_responded": 6
    },
    "pollId": "1005",
    "message": "3 I could do better",
    "value": "3"
  },
  {
    "id": "100610",
    "user": {
      "id": "1060",
      "first_name": "SUSAN",
      "last_name": "MOORE",
      "party": "LIBERTARIAN",
      "gender": "female",
      "zip": "94120"
    },
    "userId": "1060",
    "poll": {
      "id": "1006",
      "question": "How did I do in last night's debate? (0-10)",
      "start": "1459219037190",
      "end": "1459226237190",
      "polls_sent": 10,
      "polls_responded": 7
    },
    "pollId": "1006",
    "message": "8 I want to hear more about abortion",
    "value": "8"
  },
  {
    "id": "100620",
    "user": {
      "id": "1059",
      "first_name": "DEREK",
      "last_name": "TAYLOR",
      "party": "GREEN",
      "gender": "female",
      "zip": "94189"
    },
    "userId": "1059",
    "poll": {
      "id": "1006",
      "question": "How did I do in last night's debate? (0-10)",
      "start": "1459219037190",
      "end": "1459226237190",
      "polls_sent": 10,
      "polls_responded": 7
    },
    "pollId": "1006",
    "message": "0 #winning",
    "value": "0"
  },
  {
    "id": "100630",
    "user": {
      "id": "1037",
      "first_name": "GLENN",
      "last_name": "JONES",
      "party": "INDEPENDENT",
      "gender": "female",
      "zip": "94195"
    },
    "userId": "1037",
    "poll": {
      "id": "1006",
      "question": "How did I do in last night's debate? (0-10)",
      "start": "1459219037190",
      "end": "1459226237190",
      "polls_sent": 10,
      "polls_responded": 7
    },
    "pollId": "1006",
    "message": "4 #boo",
    "value": "4"
  },
  {
    "id": "100640",
    "user": {
      "id": "1036",
      "first_name": "GLENN",
      "last_name": "DAVIS",
      "party": "INDEPENDENT",
      "gender": "female",
      "zip": "94122"
    },
    "userId": "1036",
    "poll": {
      "id": "1006",
      "question": "How did I do in last night's debate? (0-10)",
      "start": "1459219037190",
      "end": "1459226237190",
      "polls_sent": 10,
      "polls_responded": 7
    },
    "pollId": "1006",
    "message": "1 I love you",
    "value": "1"
  },
  {
    "id": "100650",
    "user": {
      "id": "1063",
      "first_name": "RACHEL",
      "last_name": "ALLEN",
      "party": "GREEN",
      "gender": "female",
      "zip": "94164"
    },
    "userId": "1063",
    "poll": {
      "id": "1006",
      "question": "How did I do in last night's debate? (0-10)",
      "start": "1459219037190",
      "end": "1459226237190",
      "polls_sent": 10,
      "polls_responded": 7
    },
    "pollId": "1006",
    "message": "0 #winning",
    "value": "0"
  },
  {
    "id": "100660",
    "user": {
      "id": "1044",
      "first_name": "MINNIE",
      "last_name": "LEWIS",
      "party": "LIBERTARIAN",
      "gender": "female",
      "zip": "94178"
    },
    "userId": "1044",
    "poll": {
      "id": "1006",
      "question": "How did I do in last night's debate? (0-10)",
      "start": "1459219037190",
      "end": "1459226237190",
      "polls_sent": 10,
      "polls_responded": 7
    },
    "pollId": "1006",
    "message": "4 I could do better",
    "value": "4"
  },
  {
    "id": "100670",
    "user": {
      "id": "1093",
      "first_name": "MELANIE",
      "last_name": "HALL",
      "party": "INDEPENDENT",
      "gender": "female",
      "zip": "94173"
    },
    "userId": "1093",
    "poll": {
      "id": "1006",
      "question": "How did I do in last night's debate? (0-10)",
      "start": "1459219037190",
      "end": "1459226237190",
      "polls_sent": 10,
      "polls_responded": 7
    },
    "pollId": "1006",
    "message": "8 I could do better",
    "value": "8"
  },
  {
    "id": "100710",
    "user": {
      "id": "1052",
      "first_name": "SUSAN",
      "last_name": "JONES",
      "party": "DEMOCRAT",
      "gender": "female",
      "zip": "94136"
    },
    "userId": "1052",
    "poll": {
      "id": "1007",
      "question": "How did I do in last night's debate? (0-10)",
      "start": "1458614237190",
      "end": "1458621437190",
      "polls_sent": 10,
      "polls_responded": 3
    },
    "pollId": "1007",
    "message": "0 STOP sending me these",
    "value": "0"
  },
  {
    "id": "100720",
    "user": {
      "id": "1042",
      "first_name": "DANNY",
      "last_name": "VIK",
      "party": "DEMOCRAT",
      "gender": "female",
      "zip": "94145"
    },
    "userId": "1042",
    "poll": {
      "id": "1007",
      "question": "How did I do in last night's debate? (0-10)",
      "start": "1458614237190",
      "end": "1458621437190",
      "polls_sent": 10,
      "polls_responded": 3
    },
    "pollId": "1007",
    "message": "4 I want to hear more about abortion",
    "value": "4"
  },
  {
    "id": "100730",
    "user": {
      "id": "1049",
      "first_name": "DANNY",
      "last_name": "HALL",
      "party": "REPUBLICAN",
      "gender": "female",
      "zip": "94158"
    },
    "userId": "1049",
    "poll": {
      "id": "1007",
      "question": "How did I do in last night's debate? (0-10)",
      "start": "1458614237190",
      "end": "1458621437190",
      "polls_sent": 10,
      "polls_responded": 3
    },
    "pollId": "1007",
    "message": "1 STOP sending me these",
    "value": "1"
  },
  {
    "id": "100810",
    "user": {
      "id": "1053",
      "first_name": "DEREK",
      "last_name": "BAKER",
      "party": "GREEN",
      "gender": "female",
      "zip": "94174"
    },
    "userId": "1053",
    "poll": {
      "id": "1008",
      "question": "How did I do in last night's debate? (0-10)",
      "start": "1458614237190",
      "end": "1458621437190",
      "polls_sent": 10,
      "polls_responded": 1
    },
    "pollId": "1008",
    "message": "1 STOP sending me these",
    "value": "1"
  },
  {
    "id": "100910",
    "user": {
      "id": "1070",
      "first_name": "SUSAN",
      "last_name": "WILSON",
      "party": "REPUBLICAN",
      "gender": "female",
      "zip": "94199"
    },
    "userId": "1070",
    "poll": {
      "id": "1009",
      "question": "Do you approve of my campaign so far? (0-10)",
      "start": "1458182237190",
      "end": "1458189437190",
      "polls_sent": 10,
      "polls_responded": 8
    },
    "pollId": "1009",
    "message": "2 #boo",
    "value": "2"
  },
  {
    "id": "100920",
    "user": {
      "id": "1040",
      "first_name": "CAROLINE",
      "last_name": "HALL",
      "party": "REPUBLICAN",
      "gender": "female",
      "zip": "94165"
    },
    "userId": "1040",
    "poll": {
      "id": "1009",
      "question": "Do you approve of my campaign so far? (0-10)",
      "start": "1458182237190",
      "end": "1458189437190",
      "polls_sent": 10,
      "polls_responded": 8
    },
    "pollId": "1009",
    "message": "3 I could do better",
    "value": "3"
  },
  {
    "id": "100930",
    "user": {
      "id": "1019",
      "first_name": "RACHEL",
      "last_name": "WILLIAMS",
      "party": "INDEPENDENT",
      "gender": "female",
      "zip": "9416"
    },
    "userId": "1019",
    "poll": {
      "id": "1009",
      "question": "Do you approve of my campaign so far? (0-10)",
      "start": "1458182237190",
      "end": "1458189437190",
      "polls_sent": 10,
      "polls_responded": 8
    },
    "pollId": "1009",
    "message": "4",
    "value": "4"
  },
  {
    "id": "100940",
    "user": {
      "id": "1061",
      "first_name": "PHIL",
      "last_name": "SAKAMOTO",
      "party": "GREEN",
      "gender": "female",
      "zip": "94119"
    },
    "userId": "1061",
    "poll": {
      "id": "1009",
      "question": "Do you approve of my campaign so far? (0-10)",
      "start": "1458182237190",
      "end": "1458189437190",
      "polls_sent": 10,
      "polls_responded": 8
    },
    "pollId": "1009",
    "message": "3 #winning",
    "value": "3"
  },
  {
    "id": "100950",
    "user": {
      "id": "1007",
      "first_name": "FRANK",
      "last_name": "SAKAMOTO",
      "party": "LIBERTARIAN",
      "gender": "female",
      "zip": "94142"
    },
    "userId": "1007",
    "poll": {
      "id": "1009",
      "question": "Do you approve of my campaign so far? (0-10)",
      "start": "1458182237190",
      "end": "1458189437190",
      "polls_sent": 10,
      "polls_responded": 8
    },
    "pollId": "1009",
    "message": "7 STOP sending me these",
    "value": "7"
  },
  {
    "id": "100960",
    "user": {
      "id": "1040",
      "first_name": "CAROLINE",
      "last_name": "HALL",
      "party": "REPUBLICAN",
      "gender": "female",
      "zip": "94165"
    },
    "userId": "1040",
    "poll": {
      "id": "1009",
      "question": "Do you approve of my campaign so far? (0-10)",
      "start": "1458182237190",
      "end": "1458189437190",
      "polls_sent": 10,
      "polls_responded": 8
    },
    "pollId": "1009",
    "message": "1 I love you",
    "value": "1"
  },
  {
    "id": "100970",
    "user": {
      "id": "1038",
      "first_name": "GLENN",
      "last_name": "ALLEN",
      "party": "INDEPENDENT",
      "gender": "female",
      "zip": "94198"
    },
    "userId": "1038",
    "poll": {
      "id": "1009",
      "question": "Do you approve of my campaign so far? (0-10)",
      "start": "1458182237190",
      "end": "1458189437190",
      "polls_sent": 10,
      "polls_responded": 8
    },
    "pollId": "1009",
    "message": "10",
    "value": "10"
  },
  {
    "id": "100980",
    "user": {
      "id": "1037",
      "first_name": "GLENN",
      "last_name": "JONES",
      "party": "INDEPENDENT",
      "gender": "female",
      "zip": "94195"
    },
    "userId": "1037",
    "poll": {
      "id": "1009",
      "question": "Do you approve of my campaign so far? (0-10)",
      "start": "1458182237190",
      "end": "1458189437190",
      "polls_sent": 10,
      "polls_responded": 8
    },
    "pollId": "1009",
    "message": "7 STOP sending me these",
    "value": "7"
  }
]